githubdl/__init__.py
githubdl/api.py
githubdl/file_processing.py
githubdl/request_processing.py
githubdl/url_helpers.py
githubdl/url_processing.py
githubdl-0.1.6.dist-info/LICENSE.txt
githubdl-0.1.6.dist-info/METADATA
githubdl-0.1.6.dist-info/WHEEL
githubdl-0.1.6.dist-info/entry_points.txt
githubdl-0.1.6.dist-info/top_level.txt
githubdl-0.1.6.dist-info/RECORD
