Metadata-Version: 2.1
Name: githubdl
Version: 0.1.6
Summary: A tool for downloading individual files/directories from Github or Github Enterprise. This circumvents the requirement to clone an entire repository.
Home-page: http://githubdl.seso.io
Author: Willem van Ketwich
Author-email: willvk@gmail.com
License: MIT
Download-URL: https://github.com/wilvk/githubdl/archive/0.1.5.tar.gz
Keywords: github,github enterprise,download,file,path,git,version control,deployment,submodules,modules
Platform: UNKNOWN
Classifier: Development Status :: 3 - Alpha
Classifier: Intended Audience :: Developers
Classifier: Topic :: Software Development :: Build Tools
Classifier: License :: OSI Approved :: MIT License
Classifier: Programming Language :: Python :: 3.4
Classifier: Programming Language :: Python :: 3.5
Classifier: Programming Language :: Python :: 3.6
Requires-Python: >=3.4
Requires-Dist: requests
Provides-Extra: dev
Provides-Extra: test
Requires-Dist: nose ; extra == 'test'
